Retail_Management/__init__.py
Retail_Management/admin.py
Retail_Management/apps.py
Retail_Management/models.py
Retail_Management/tests.py
Retail_Management/views.py
Retail_Management/migrations/0001_initial.py
Retail_Management/migrations/__init__.py
Royal_Cashews-1.0.0.dist-info/LICENSE
Royal_Cashews-1.0.0.dist-info/METADATA
Royal_Cashews-1.0.0.dist-info/WHEEL
Royal_Cashews-1.0.0.dist-info/top_level.txt
Royal_Cashews-1.0.0.dist-info/RECORD
